polotsk/__init__.py
polotsk/__main__.py
polotsk/external.py
polotsk/internal.py
polotsk/main.py
polotsk_admin/__init__.py
polotsk_admin/main.py
polotsk_admin/app/main/__init__.py
polotsk_admin/app/main/main.py
polotsk-1.1.1.dist-info/LICENSE
polotsk-1.1.1.dist-info/METADATA
polotsk-1.1.1.dist-info/WHEEL
polotsk-1.1.1.dist-info/top_level.txt
polotsk-1.1.1.dist-info/RECORD
